request_signer/__init__.py
request_signer/core/__init__.py
request_signer/core/exceptions.py
request_signer/core/request.py
request_signer/core/signer.py
request_signer/django_utils/__init__.py
request_signer/django_utils/permissions.py
request_signer/django_utils/signed_request.py
request_signer/flask_utils/__init__.py
request_signer/flask_utils/permissions.py
request_signer/flask_utils/signed_request.py
request_signer-0.4.1.dist-info/LICENSE
request_signer-0.4.1.dist-info/METADATA
request_signer-0.4.1.dist-info/WHEEL
request_signer-0.4.1.dist-info/top_level.txt
request_signer-0.4.1.dist-info/RECORD
