Metadata-Version: 2.1
Name: request-signer
Version: 0.4.1
Summary: Request signing for intersystem communications.
Home-page: https://github.com/Fitspot/request_signer
Author: Tenspot Dev
Author-email: caleb@tenspot.com
License: UNKNOWN
Platform: UNKNOWN
Classifier: Programming Language :: Python :: 3
Classifier: License :: OSI Approved :: MIT License
Classifier: Operating System :: OS Independent
Requires-Python: >=3.8
License-File: LICENSE
Requires-Dist: requests
Requires-Dist: simplejson
